{
  "type": "card-type",
  "engine": "card-type",
  "direction": "high-wins",
  "target": 500,
  "multiRound": true,
  "players": { "min": 2, "max": 10 },
  "cardTypes": [
    { "id": "num1", "name": { "en": "Number 1-9", "zh": "数字 1-9" }, "value": 1, "group": "number" },
    { "id": "draw1", "name": { "en": "Draw One", "zh": "+1" }, "value": 10, "group": "action" },
    { "id": "draw5", "name": { "en": "Draw Five", "zh": "+5" }, "value": 10, "group": "action" },
    { "id": "reverse", "name": { "en": "Reverse", "zh": "反转" }, "value": 20, "group": "action" },
    { "id": "skip", "name": { "en": "Skip", "zh": "禁止" }, "value": 20, "group": "action" },
    { "id": "skip-all", "name": { "en": "Skip Everyone", "zh": "全体禁止" }, "value": 20, "group": "action" },
    { "id": "flip", "name": { "en": "Flip", "zh": "翻转" }, "value": 20, "group": "action" },
    { "id": "wild", "name": { "en": "Wild", "zh": "万能牌" }, "value": 40, "group": "wild" },
    { "id": "wild-draw2", "name": { "en": "Wild Draw Two", "zh": "万能+2" }, "value": 50, "group": "wild" },
    { "id": "wild-draw-color", "name": { "en": "Wild Draw Color", "zh": "万能抽色" }, "value": 50, "group": "wild" }
  ],
  "filters": [
    {
      "id": "group",
      "name": { "en": "Type", "zh": "类型" },
      "field": "group",
      "values": [
        { "id": "all", "name": { "en": "All", "zh": "全部" } },
        { "id": "number", "name": { "en": "Numbers", "zh": "数字牌" } },
        { "id": "action", "name": { "en": "Action", "zh": "功能牌" } },
        { "id": "wild", "name": { "en": "Wild", "zh": "万能牌" } }
      ]
    }
  ]
}
